ecg_tools/__init__.py
ecg_tools/_nbdev.py
ecg_tools/card.py
ecg_tools/deck.py
ecg_tools-0.0.1.dist-info/LICENSE
ecg_tools-0.0.1.dist-info/METADATA
ecg_tools-0.0.1.dist-info/WHEEL
ecg_tools-0.0.1.dist-info/entry_points.txt
ecg_tools-0.0.1.dist-info/top_level.txt
ecg_tools-0.0.1.dist-info/RECORD
