Metadata-Version: 2.1
Name: ecg-tools
Version: 0.0.1
Summary: "A description of your project"
Home-page: https://github.com/fmenegui/ecg_tools/tree/master/
Author: Felipe Dias
Author-email: felipe.dias@engenharia.ufjf.br
License: Apache Software License 2.0
Keywords: ecg
Platform: UNKNOWN
Classifier: Development Status :: 3 - Alpha
Classifier: Intended Audience :: Developers
Classifier: License :: OSI Approved :: Apache Software License
Classifier: Natural Language :: English
Classifier: Programming Language :: Python :: 3.6
Classifier: Programming Language :: Python :: 3.7
Classifier: Programming Language :: Python :: 3.8
Requires-Python: >=3.6
